setup.cfg
setup.py
leafly/__init__.py
leafly/leafly.py
leafly/metadata.py
leafly.egg-info/PKG-INFO
leafly.egg-info/SOURCES.txt
leafly.egg-info/dependency_links.txt
leafly.egg-info/requires.txt
leafly.egg-info/top_level.txt