Metadata-Version: 1.1
Name: leafly
Version: 0.0.4
Summary: A Python wrapper for Leafly
Home-page: http://github.com/lionheart/python-leafly
Author: Dan Loewenherz
Author-email: dan@lionheartsw.com
License: Apache 2.0
Keywords: leafly
Platform: UNKNOWN
Classifier: Development Status :: 5 - Production/Stable
Classifier: Environment :: Console
Classifier: Intended Audience :: Developers
Classifier: Natural Language :: English
Classifier: Operating System :: OS Independent
Classifier: Programming Language :: Python
Classifier: Topic :: Software Development :: Libraries :: Python Modules
Classifier: Topic :: Internet :: WWW/HTTP :: Dynamic Content :: CGI Tools/Libraries
Classifier: Topic :: Utilities
Classifier: License :: OSI Approved :: Apache Software License
